rest_framework_toolbox/__init__.py
rest_framework_toolbox/core/__init__.py
rest_framework_toolbox/core/fields.py
rest_framework_toolbox/core/utils.py
rest_framework_toolbox/core/models/__init__.py
rest_framework_toolbox/core/models/_meta.py
rest_framework_toolbox/core/models/main.py
rest_framework_toolbox/email/__init__.py
rest_framework_toolbox/email/admin.py
rest_framework_toolbox/email/apps.py
rest_framework_toolbox/email/models.py
rest_framework_toolbox/email/server.py
rest_framework_toolbox/email/urls.py
rest_framework_toolbox/email/views.py
rest_framework_toolbox/handlers/__init__.py
rest_framework_toolbox/handlers/error_handler/__init__.py
rest_framework_toolbox/handlers/error_handler/_config.py
rest_framework_toolbox/handlers/error_handler/error_handler.py
rest_framework_toolbox/handlers/error_handler/main.py
rest_framework_toolbox/handlers/linker/__init__.py
rest_framework_toolbox/handlers/linker/main.py
rest_framework_toolbox/handlers/renderer/__init__.py
rest_framework_toolbox/handlers/renderer/main.py
rest_framework_toolbox/log/__init__.py
rest_framework_toolbox/log/main.py
rest_framework_toolbox/swagger/__init__.py
rest_framework_toolbox/swagger/main.py
rest_framework_toolbox/swagger/schema.py
rest_framework_toolbox/swagger/schema_errors.py
rest_framework_toolbox-0.3208.dist-info/LICENSE
rest_framework_toolbox-0.3208.dist-info/METADATA
rest_framework_toolbox-0.3208.dist-info/WHEEL
rest_framework_toolbox-0.3208.dist-info/top_level.txt
rest_framework_toolbox-0.3208.dist-info/RECORD
