Metadata-Version: 2.1
Name: rest_framework_toolbox
Version: 0.3208
Summary: A custom toolbox with ready to use utilities.
Home-page: https://github.com/zaki-x86/django_restful_toolbox.git
Author: Mohamed Zaki
Author-email: zaki.x86@gmail.com
License: MIT License
Classifier: Framework :: Django
Classifier: Programming Language :: Python :: 3
License-File: LICENSE
Requires-Dist: Django >=3.2
Requires-Dist: djangorestframework >=3.12.4
Requires-Dist: markdown >=3.3.4
